odoo/addons/project_description/README.rst
odoo/addons/project_description/__init__.py
odoo/addons/project_description/__manifest__.py
odoo/addons/project_description/i18n/ca.po
odoo/addons/project_description/i18n/cs_CZ.po
odoo/addons/project_description/i18n/de.po
odoo/addons/project_description/i18n/es.po
odoo/addons/project_description/i18n/es_CO.po
odoo/addons/project_description/i18n/es_MX.po
odoo/addons/project_description/i18n/fi.po
odoo/addons/project_description/i18n/fr.po
odoo/addons/project_description/i18n/gl.po
odoo/addons/project_description/i18n/hr.po
odoo/addons/project_description/i18n/it.po
odoo/addons/project_description/i18n/nb.po
odoo/addons/project_description/i18n/nl.po
odoo/addons/project_description/i18n/nl_NL.po
odoo/addons/project_description/i18n/project_description.pot
odoo/addons/project_description/i18n/pt.po
odoo/addons/project_description/i18n/pt_BR.po
odoo/addons/project_description/i18n/pt_PT.po
odoo/addons/project_description/i18n/sl.po
odoo/addons/project_description/i18n/tr.po
odoo/addons/project_description/i18n/zh_CN.po
odoo/addons/project_description/models/__init__.py
odoo/addons/project_description/models/project.py
odoo/addons/project_description/readme/CONTRIBUTORS.rst
odoo/addons/project_description/readme/DESCRIPTION.rst
odoo/addons/project_description/readme/USAGE.rst
odoo/addons/project_description/static/description/icon.png
odoo/addons/project_description/static/description/image.png
odoo/addons/project_description/static/description/index.html
odoo/addons/project_description/views/project_view.xml
odoo13_addon_project_description-13.0.1.0.1.dev6.dist-info/METADATA
odoo13_addon_project_description-13.0.1.0.1.dev6.dist-info/WHEEL
odoo13_addon_project_description-13.0.1.0.1.dev6.dist-info/top_level.txt
odoo13_addon_project_description-13.0.1.0.1.dev6.dist-info/RECORD
